riva_asrlib_decoder-0.4.4.dist-info/top_level.txt
riva_asrlib_decoder-0.4.4.dist-info/LICENSE-2.0.txt
riva_asrlib_decoder-0.4.4.dist-info/METADATA
riva_asrlib_decoder-0.4.4.dist-info/WHEEL
riva_asrlib_decoder-0.4.4.dist-info/RECORD
riva/asrlib/decoder/python_decoder.cpython-311-x86_64-linux-gnu.so
riva/asrlib/decoder/reproducer.py
riva/asrlib/decoder/__init__.py
riva/asrlib/decoder/test_decoder.py
riva/asrlib/decoder/test_graph_construction.py
riva/asrlib/decoder/scripts/prepare_TLG_fst/__init__.py
riva/asrlib/decoder/scripts/prepare_TLG_fst/prep_subw_lexicon.sh
riva/asrlib/decoder/scripts/prepare_TLG_fst/path.sh
riva/asrlib/decoder/scripts/prepare_TLG_fst/mkgraph_ctc.sh
riva/asrlib/decoder/scripts/prepare_TLG_fst/bin/fstconvert
riva/asrlib/decoder/scripts/prepare_TLG_fst/bin/transcripts-to-fsts
riva/asrlib/decoder/scripts/prepare_TLG_fst/bin/fstcompile
riva/asrlib/decoder/scripts/prepare_TLG_fst/bin/fstdeterminizestar
riva/asrlib/decoder/scripts/prepare_TLG_fst/bin/fsttablecompose
riva/asrlib/decoder/scripts/prepare_TLG_fst/bin/fstrmepslocal
riva/asrlib/decoder/scripts/prepare_TLG_fst/bin/fstaddselfloops
riva/asrlib/decoder/scripts/prepare_TLG_fst/bin/fstminimizeencoded
riva/asrlib/decoder/scripts/prepare_TLG_fst/bin/arpa2fst
riva/asrlib/decoder/scripts/prepare_TLG_fst/bin/fstcompose
riva/asrlib/decoder/scripts/prepare_TLG_fst/bin/fstarcsort
riva/asrlib/decoder/scripts/prepare_TLG_fst/bin/fstisstochastic
riva/asrlib/decoder/scripts/prepare_TLG_fst/local/ctc_compile_dict_token.sh
riva/asrlib/decoder/scripts/prepare_TLG_fst/local/make_ctc_alignment_graphs.sh
riva/asrlib/decoder/scripts/prepare_TLG_fst/local/__init__.py
riva/asrlib/decoder/scripts/prepare_TLG_fst/local/parse_options.sh
riva/asrlib/decoder/scripts/prepare_TLG_fst/local/identity_token_fst.py
riva/asrlib/decoder/scripts/prepare_TLG_fst/local/ctc_token_fst.py
riva/asrlib/decoder/scripts/prepare_TLG_fst/local/ctc_compact_token_fst.py
riva/asrlib/decoder/scripts/prepare_TLG_fst/local/add_lm_disambig.py
riva/asrlib/decoder/scripts/prepare_TLG_fst/local/subw_tokenize_text.py
riva/asrlib/decoder/scripts/prepare_TLG_fst/local/prepare_dict_ctc.sh
