Metadata-Version: 2.1
Name: riva-asrlib-decoder
Version: 0.4.4
Summary: Implementation of https://arxiv.org/abs/1910.10032
Home-page: https://github.com/nvidia-riva/riva-asrlib-decoder
Author: NVIDIA
Author-email: dgalvez@nvidia.com
Keywords: ASR,CUDA,WFST,Decoder
Requires-Python: >=3.7
License-File: LICENSE-2.0.txt
Requires-Dist: sentencepiece
Provides-Extra: testing
Requires-Dist: pytest ; extra == 'testing'
Requires-Dist: kaldi-io ; extra == 'testing'
Requires-Dist: more-itertools ; extra == 'testing'
Requires-Dist: nemo-toolkit[asr] ; extra == 'testing'
Requires-Dist: torchaudio ; extra == 'testing'
